arcsecond/__init__.py
arcsecond/__version__.py
arcsecond/cli.py
arcsecond/errors.py
arcsecond/options.py
arcsecond/api/__init__.py
arcsecond/api/config.py
arcsecond/api/constants.py
arcsecond/api/endpoint.py
arcsecond/api/main.py
arcsecond/cloud/__init__.py
arcsecond/cloud/auth.py
arcsecond/cloud/resources.py
arcsecond/cloud/uploads.py
arcsecond/cloud/uploader/__init__.py
arcsecond/cloud/uploader/constants.py
arcsecond/cloud/uploader/context.py
arcsecond/cloud/uploader/errors.py
arcsecond/cloud/uploader/logger.py
arcsecond/cloud/uploader/uploader.py
arcsecond/cloud/uploader/utils.py
arcsecond/cloud/uploader/walker.py
arcsecond/cloud/uploader/allskycameraimages/__init__.py
arcsecond/cloud/uploader/allskycameraimages/context.py
arcsecond/cloud/uploader/allskycameraimages/errors.py
arcsecond/cloud/uploader/allskycameraimages/uploader.py
arcsecond/cloud/uploader/allskycameraimages/utils.py
arcsecond/cloud/uploader/datafiles/__init__.py
arcsecond/cloud/uploader/datafiles/context.py
arcsecond/cloud/uploader/datafiles/errors.py
arcsecond/cloud/uploader/datafiles/uploader.py
arcsecond/cloud/uploader/datafiles/utils.py
arcsecond/hosting/__init__.py
arcsecond/hosting/checks.py
arcsecond/hosting/constants.py
arcsecond/hosting/local.py
arcsecond/hosting/main.py
arcsecond/hosting/setup.py
arcsecond/hosting/utils.py
arcsecond/hosting/validation.py
arcsecond/hosting/docker/__init__.py
arcsecond/hosting/docker/constants.py
arcsecond/hosting/docker/containers.py
arcsecond/hosting/docker/docker-compose.yml
arcsecond/hosting/docker/images.py
arcsecond/hosting/docker/utils.py
arcsecond/hosting/keygen/__init__.py
arcsecond/hosting/keygen/client.py
arcsecond/hosting/keygen/utils.py
arcsecond-3.7.1.dist-info/licenses/LICENSE
tests/api/__init__.py
tests/api/test_api.py
tests/api/test_api_endpoint.py
tests/api/test_config.py
tests/cloud/__init__.py
tests/cloud/uploader/__init__.py
tests/cloud/uploader/allskycameraimages/__init__.py
tests/cloud/uploader/allskycameraimages/test_context.py
arcsecond-3.7.1.dist-info/METADATA
arcsecond-3.7.1.dist-info/WHEEL
arcsecond-3.7.1.dist-info/entry_points.txt
arcsecond-3.7.1.dist-info/top_level.txt
arcsecond-3.7.1.dist-info/RECORD
