Metadata-Version: 2.4
Name: arcsecond
Version: 3.7.1
Summary: CLI for arcsecond.io
Home-page: https://github.com/arcsecond-io/cli
Author: Cedric Foellmi
Author-email: Cedric Foellmi <cedric@arcsecond.io>
License: MIT License
Project-URL: Homepage, https://github.com/arcsecond-io/cli
Project-URL: Issues, https://github.com/arcsecond-io/cli/issues
Project-URL: Documentation, https://docs.arcsecond.io
Platform: any
Classifier: Development Status :: 5 - Production/Stable
Classifier: Environment :: Console
Classifier: Intended Audience :: Developers
Classifier: License :: OSI Approved :: MIT License
Classifier: Operating System :: OS Independent
Classifier: Programming Language :: Python :: 3
Classifier: Topic :: Software Development :: Libraries :: Python Modules
Requires-Python: >=3.9
License-File: LICENSE
Requires-Dist: click>=8
Requires-Dist: configparser
Requires-Dist: docker
Requires-Dist: httpx
Requires-Dist: tqdm<5.0.0,>=4.67.1
Requires-Dist: py-machineid
Requires-Dist: wait-for-it
Dynamic: author
Dynamic: home-page
Dynamic: license-file
Dynamic: platform
